xs/__init__.py
xs_api-1.1.0.dist-info/METADATA
xs_api-1.1.0.dist-info/RECORD
xs_api-1.1.0.dist-info/WHEEL
xs_api-1.1.0.dist-info/top_level.txt
